heist/__init__.py
heist/__main__.py
heist/hemiplasytool.py
heist/seqtools.py
heist_hemiplasy-0.3.1.dist-info/LICENSE
heist_hemiplasy-0.3.1.dist-info/METADATA
heist_hemiplasy-0.3.1.dist-info/WHEEL
heist_hemiplasy-0.3.1.dist-info/entry_points.txt
heist_hemiplasy-0.3.1.dist-info/top_level.txt
heist_hemiplasy-0.3.1.dist-info/RECORD
