Metadata-Version: 2.1
Name: heist-hemiplasy
Version: 0.3.1
Summary: Hemiplasy Inference Simulation Tool. For characterising hemiplasy given traits mapped onto a species tree
Home-page: https://github.com/mhibbins/hemiplasytool
Author: Matt Gibson, Mark Hibbins
Author-email: matthewjsgibson@gmail.com, mhibbins@iu.edu
License: MIT
Keywords: phylogenetics evolution hemiplasy homoplasy
Platform: UNKNOWN
Requires-Dist: biopython
Requires-Dist: numpy
Requires-Dist: matplotlib
Requires-Dist: ete3
